nyaasi_rss/__init__.py
nyaasi_rss/exceptions.py
nyaasi_rss/fetcher.py
nyaasi_rss/models.py
nyaasi_rss-0.1.0.dist-info/METADATA
nyaasi_rss-0.1.0.dist-info/WHEEL
nyaasi_rss-0.1.0.dist-info/top_level.txt
nyaasi_rss-0.1.0.dist-info/RECORD
