Metadata-Version: 2.1
Name: nyaasi-rss
Version: 0.1.0
Summary: Add your description here
Home-page: https://github.com/praveensenpai/nyaasi_rss
Author: Praveen
Author-email: pvnt20@gmail.com
Requires-Python: >=3.11
Requires-Dist: httpx>=0.27.2
